nianet/__init__.py
nianet/autoencoder.py
nianet/helper.py
nianet/problem.py
nianet-1.1.4.dist-info/LICENSE
nianet-1.1.4.dist-info/WHEEL
nianet-1.1.4.dist-info/METADATA
nianet-1.1.4.dist-info/RECORD
