Metadata-Version: 2.1
Name: nianet
Version: 1.1.4
Summary: Designing and constructing neural network topologies using nature-inspired algorithms
Home-page: https://github.com/SasoPavlic/NiaNet
Keywords: adaptation,deep learning,nature-inspired algorithms,neural networks,torch
Author: Sašo Pavlič
Author-email: saso.pavlic@student.um.si
Requires-Python: >=3.8,<3.11
Classifier: Programming Language :: Python :: 3
Classifier: Programming Language :: Python :: 3.10
Classifier: Programming Language :: Python :: 3.8
Classifier: Programming Language :: Python :: 3.9
Requires-Dist: matplotlib (>=3.5.1,<4.0.0)
Requires-Dist: niapy (>=2.0.4,<3.0.0)
Requires-Dist: numpy (>=1.22.3,<2.0.0)
Requires-Dist: scikit-learn (>=1.0.2,<2.0.0)
Requires-Dist: torch (>=1.13.1,<2.0.0)
Project-URL: Repository, https://github.com/SasoPavlic/NiaNet
